setup.py
AQube_Core/__init__.py
AQube_Core/__main__.py
AQube_Core/config.py
AQube_Core/device.py
AQube_Core/handler.py
AQube_Core/utils.py
aqube.egg-info/PKG-INFO
aqube.egg-info/SOURCES.txt
aqube.egg-info/dependency_links.txt
aqube.egg-info/requires.txt
aqube.egg-info/top_level.txt