Metadata-Version: 1.0
Name: aqube
Version: 0.1.0
Summary: a flexible tool to operate android
Home-page: https://github.com/williamfzc/AQube_Core
Author: williamfzc
Author-email: fengzc@vip.qq.com
License: UNKNOWN
Platform: UNKNOWN
